sober/__init__.py
sober/_evaluator.py
sober/_evolver.py
sober/_evolver_pymoo.py
sober/_io_managers.py
sober/_logger.py
sober/_multiplier.py
sober/_simulator.py
sober/_tools.py
sober/_typing.py
sober/config.py
sober/input.py
sober/output.py
sober/problem.py
sober-0.3.0.dist-info/METADATA
sober-0.3.0.dist-info/WHEEL
sober-0.3.0.dist-info/licenses/LICENSE.txt
sober-0.3.0.dist-info/RECORD
