Metadata-Version: 2.4
Name: sober
Version: 0.3.0
Summary: sober optimises built environment robustly
Project-URL: homepage, https://github.com/airallergy/sober
Project-URL: repository, https://github.com/airallergy/sober
Author-email: Cheng Cui <cheng.cui.95@gmail.com>
License: MIT
License-File: LICENSE.txt
Requires-Python: >=3.12
Requires-Dist: eppy~=0.5.63
Requires-Dist: numpy==2.*
Requires-Dist: psutil==6.*
Requires-Dist: pymoo~=0.6.1
Requires-Dist: scipy~=1.13
